ndimpute/__init__.py
ndimpute/_interval.py
ndimpute/_parametric.py
ndimpute/_preprocess.py
ndimpute/_ros_left.py
ndimpute/_ros_mixed.py
ndimpute/_ros_right.py
ndimpute/_substitution.py
ndimpute/_turnbull.py
ndimpute/api.py
ndimpute-0.1.0.dist-info/LICENSE
ndimpute-0.1.0.dist-info/METADATA
ndimpute-0.1.0.dist-info/WHEEL
ndimpute-0.1.0.dist-info/RECORD
