Metadata-Version: 2.1
Name: ndimpute
Version: 0.1.0
Summary: A package for imputing arbitrarily censored data
Home-page: https://github.com/LukeAFullard/ndimpute
Author: Luke Fullard
Requires-Python: >=3.9
Classifier: Programming Language :: Python :: 3
Classifier: Programming Language :: Python :: 3.9
Classifier: Programming Language :: Python :: 3.10
Classifier: Programming Language :: Python :: 3.11
Classifier: Programming Language :: Python :: 3.12
Provides-Extra: viz
Requires-Dist: matplotlib ; extra == "viz"
Requires-Dist: numpy (>=1.24.0)
Requires-Dist: pandas (>=2.0.0)
Requires-Dist: scipy (>=1.13.0)
Requires-Dist: seaborn ; extra == "viz"
Project-URL: Repository, https://github.com/LukeAFullard/ndimpute
